{
  "2026-03-18": {
    "5545647021": { "name": "Ku Ku", "count": 5 },
    "5251501400": { "name": " NawLyaWarHtoo( FD )", "count": 5 },
    "1966382979": { "name": "John", "count": 4 },
    "7406648934": { "name": "дѕќеҐЅ рџ‘‘", "count": 11 },
    "2115532359": { "name": "жЂќжЂќ", "count": 1 },
    "7300796372": { "name": "и‹Џи‹ЏжќҐ", "count": 12 },
    "8591427572": { "name": " и‹—ж•Џеє·", "count": 17 },
    "7375446542": { "name": "Banzou", "count": 15 },
    "8504004122": { "name": " зЋ‹е§“ (FD)", "count": 0 },
    "5541863981": { "name": " Kee is livingthing(FD)", "count": 1 },
    "7450025463": { "name": " Amg AnnaрџђЅрџЊјрџЄђ", "count": 1 },
    "1727971756": { "name": "Nico", "count": 3 }
  },

  "2026-03": {
    "5545647021": { "name": "Ku Ku", "count": 5 },
    "5251501400": { "name": " NawLyaWarHtoo( FD )", "count": 5 },
    "1966382979": { "name": "John", "count": 4 },
    "7406648934": { "name": "дѕќеҐЅ рџ‘‘", "count": 11 },
    "2115532359": { "name": "жЂќжЂќ", "count": 1 },
    "7300796372": { "name": "и‹Џи‹ЏжќҐ", "count": 12 },
    "8591427572": { "name": " и‹—ж•Џеє·", "count": 17 },
    "7375446542": { "name": "Banzou", "count": 15 },
    "8504004122": { "name": " зЋ‹е§“ (FD)", "count": 0 },
    "5541863981": { "name": " Kee is livingthing(FD)", "count": 1 },
    "7450025463": { "name": " Amg AnnaрџђЅрџЊјрџЄђ", "count": 1 },
    "1727971756": { "name": "Nico", "count": 3 }
  }
}

